optimus_jbscorer/__init__.py
optimus_jbscorer/example.py
optimus_jbscorer-0.0.2.dist-info/METADATA
optimus_jbscorer-0.0.2.dist-info/WHEEL
optimus_jbscorer-0.0.2.dist-info/top_level.txt
optimus_jbscorer-0.0.2.dist-info/RECORD
