Metadata-Version: 2.4
Name: optimus-jbscorer
Version: 0.0.2
Summary: Optimus: A semantic and harmfulness-based metric for evaluating LLM jailbreak prompts
Author-email: Ismail Hossain <ihossain@miners.utep.edu>
License-Expression: MIT
Project-URL: Homepage, https://github.com/ismail102/optimus-pypi
Keywords: LLM,jailbreak,AI safety,adversarial prompts,robust evaluation,semantic similarity
Classifier: Development Status :: 4 - Beta
Classifier: Intended Audience :: Science/Research
Classifier: Topic :: Scientific/Engineering :: Artificial Intelligence
Classifier: Programming Language :: Python :: 3
Classifier: Programming Language :: Python :: 3.9
Classifier: Programming Language :: Python :: 3.10
Classifier: Programming Language :: Python :: 3.11
Classifier: Programming Language :: Python :: 3.12
Classifier: Operating System :: OS Independent
Requires-Python: >=3.9
Requires-Dist: torch
Requires-Dist: transformers
Requires-Dist: sentence-transformers
Requires-Dist: numpy
